setup.py
MwasUtilities/__init__.py
MwasUtilities/test.py
MwasUtilities/utilities.py
MwasUtilities.egg-info/PKG-INFO
MwasUtilities.egg-info/SOURCES.txt
MwasUtilities.egg-info/dependency_links.txt
MwasUtilities.egg-info/top_level.txt