Metadata-Version: 1.0
Name: MwasUtilities
Version: 0.0.6
Summary: it is used to get object from dict recusively for with get method
Home-page: UNKNOWN
Author: mwas
Author-email: francismwangi152@gmail.com
License: UNKNOWN
Platform: UNKNOWN
